aiwatchdog_sdk/__init__.py
aiwatchdog_sdk-0.0.1.dist-info/METADATA
aiwatchdog_sdk-0.0.1.dist-info/WHEEL
aiwatchdog_sdk-0.0.1.dist-info/top_level.txt
aiwatchdog_sdk-0.0.1.dist-info/RECORD
